MANIFEST.in
README.md
setup.py
tox.ini
pytest_ghostinspector.egg-info/PKG-INFO
pytest_ghostinspector.egg-info/SOURCES.txt
pytest_ghostinspector.egg-info/dependency_links.txt
pytest_ghostinspector.egg-info/entry_points.txt
pytest_ghostinspector.egg-info/requires.txt
pytest_ghostinspector.egg-info/top_level.txt
pytest_gi/__init__.py
pytest_gi/plugin.py
tests/conftest.py
tests/conftest.pyc
tests/test_ghostinspector.py
tests/__pycache__/conftest.cpython-33.pyc
tests/__pycache__/conftest.cpython-34.pyc
tests/__pycache__/conftest.cpython-35.pyc
tests/__pycache__/test_ghostinspector.cpython-26-PYTEST.pyc
tests/__pycache__/test_ghostinspector.cpython-27-PYTEST.pyc
tests/__pycache__/test_ghostinspector.cpython-33-PYTEST.pyc
tests/__pycache__/test_ghostinspector.cpython-34-PYTEST.pyc
tests/__pycache__/test_ghostinspector.cpython-35-PYTEST.pyc